odoo/addons/web_m2x_options_manager/README.rst
odoo/addons/web_m2x_options_manager/__init__.py
odoo/addons/web_m2x_options_manager/__manifest__.py
odoo/addons/web_m2x_options_manager/hooks.py
odoo/addons/web_m2x_options_manager/tools.py
odoo/addons/web_m2x_options_manager/demo/res_partner_demo_view.xml
odoo/addons/web_m2x_options_manager/i18n/it.po
odoo/addons/web_m2x_options_manager/i18n/web_m2x_options_manager.pot
odoo/addons/web_m2x_options_manager/models/__init__.py
odoo/addons/web_m2x_options_manager/models/ir_model.py
odoo/addons/web_m2x_options_manager/models/ir_model_fields.py
odoo/addons/web_m2x_options_manager/models/ir_ui_view.py
odoo/addons/web_m2x_options_manager/models/m2x_create_edit_option.py
odoo/addons/web_m2x_options_manager/readme/CONTRIBUTORS.md
odoo/addons/web_m2x_options_manager/readme/DESCRIPTION.md
odoo/addons/web_m2x_options_manager/readme/USAGE.md
odoo/addons/web_m2x_options_manager/security/ir.model.access.csv
odoo/addons/web_m2x_options_manager/static/description/icon.png
odoo/addons/web_m2x_options_manager/static/description/index.html
odoo/addons/web_m2x_options_manager/tests/__init__.py
odoo/addons/web_m2x_options_manager/tests/common.py
odoo/addons/web_m2x_options_manager/tests/test_ir_model.py
odoo/addons/web_m2x_options_manager/tests/test_ir_model_fields.py
odoo/addons/web_m2x_options_manager/tests/test_m2x_create_edit_option.py
odoo/addons/web_m2x_options_manager/views/ir_model.xml
odoo/addons/web_m2x_options_manager/views/m2x_create_edit_option.xml
odoo_addon_web_m2x_options_manager-17.0.1.0.0.2.dist-info/METADATA
odoo_addon_web_m2x_options_manager-17.0.1.0.0.2.dist-info/WHEEL
odoo_addon_web_m2x_options_manager-17.0.1.0.0.2.dist-info/top_level.txt
odoo_addon_web_m2x_options_manager-17.0.1.0.0.2.dist-info/RECORD
