Metadata-Version: 2.1
Name: odoo-addon-web_m2x_options_manager
Version: 17.0.1.0.0.2
Requires-Python: >=3.10
Requires-Dist: odoo-addon-base_view_inheritance_extension>=17.0dev,<17.1dev
Requires-Dist: odoo-addon-web_m2x_options>=17.0dev,<17.1dev
Requires-Dist: odoo>=17.0a,<17.1dev
Summary: Adds an interface to manage the "Create" and "Create and Edit" options for specific models and fields.
Home-page: https://github.com/OCA/web
License: AGPL-3
Author: Camptocamp, Odoo Community Association (OCA)
Author-email: support@odoo-community.org
Classifier: Programming Language :: Python
Classifier: Framework :: Odoo
Classifier: Framework :: Odoo :: 17.0
Classifier: License :: OSI Approved :: GNU Affero General Public License v3
